[
  {
    "question": "加入门槛是什么？",
    "answer": "欢迎持续创作的 X 创作者，需至少有 20 条原创推文。提交申请后，我们会在 48 小时内完成审核。",
    "lang": "zh"
  },
  {
    "question": "学习路径如何安排？",
    "answer": "基础模块包含写作体系、增长飞轮、运营仪式。高级模块涵盖商业化、团队协作与数据仪表板。",
    "lang": "zh"
  },
  {
    "question": "时间投入需要多少？",
    "answer": "每周 2 次共学（每次 60 分钟）、1 次写作点评（30 分钟）、日常讨论按需参与。",
    "lang": "zh"
  },
  {
    "question": "退出与退款怎么处理？",
    "answer": "首月提供 7 天冷静期体验，不满意可全额退款。此后按季度结算。",
    "lang": "zh"
  },
  {
    "question": "隐私与守则有哪些？",
    "answer": "所有案例需脱敏处理；禁止泄露成员数据；公开内容需二次确认。",
    "lang": "zh"
  }
]
